LICENSE
path_ignore_pattern/__init__.py
path_ignore_pattern/py.typed
path_ignore_pattern-0.0.1.1.dist-info/LICENSE
path_ignore_pattern-0.0.1.1.dist-info/METADATA
path_ignore_pattern-0.0.1.1.dist-info/WHEEL
path_ignore_pattern-0.0.1.1.dist-info/RECORD
