Metadata-Version: 2.1
Name: path_ignore_pattern
Version: 0.0.1.1
Summary: Python path ignore pattern.
Home-page: https://github.com/ChenyangGao/web-mount-packs/tree/main/python-module/path_ignore_pattern
License: MIT
Keywords: gitignore,ignore,pattern
Author: ChenyangGao
Author-email: wosiwujm@gmail.com
Requires-Python: >=3.10,<4.0
Classifier: Development Status :: 5 - Production/Stable
Classifier: Intended Audience :: Developers
Classifier: License :: OSI Approved :: MIT License
Classifier: Operating System :: OS Independent
Classifier: Programming Language :: Python
Classifier: Programming Language :: Python :: 3
Classifier: Programming Language :: Python :: 3.10
Classifier: Programming Language :: Python :: 3.11
Classifier: Programming Language :: Python :: 3.12
Classifier: Programming Language :: Python :: 3 :: Only
Classifier: Topic :: Software Development
Classifier: Topic :: Software Development :: Libraries
Classifier: Topic :: Software Development :: Libraries :: Python Modules
Requires-Dist: glob_pattern (>=0.0.2)
Project-URL: Repository, https://github.com/ChenyangGao/web-mount-packs/tree/main/python-module/path_ignore_pattern
